langbot_plugin/__init__.py
langbot_plugin/version.py
langbot_plugin/api/__init__.py
langbot_plugin/api/definition/__init__.py
langbot_plugin/api/definition/plugin.py
langbot_plugin/api/definition/abstract/__init__.py
langbot_plugin/api/definition/abstract/platform/__init__.py
langbot_plugin/api/definition/abstract/platform/adapter.py
langbot_plugin/api/definition/abstract/platform/event_logger.py
langbot_plugin/api/definition/components/__init__.py
langbot_plugin/api/definition/components/base.py
langbot_plugin/api/definition/components/manifest.py
langbot_plugin/api/definition/components/command/__init__.py
langbot_plugin/api/definition/components/command/command.py
langbot_plugin/api/definition/components/common/__init__.py
langbot_plugin/api/definition/components/common/event_listener.py
langbot_plugin/api/definition/components/knowledge_retriever/__init__.py
langbot_plugin/api/definition/components/knowledge_retriever/retriever.py
langbot_plugin/api/definition/components/tool/__init__.py
langbot_plugin/api/definition/components/tool/tool.py
langbot_plugin/api/entities/__init__.py
langbot_plugin/api/entities/context.py
langbot_plugin/api/entities/events.py
langbot_plugin/api/entities/builtin/__init__.py
langbot_plugin/api/entities/builtin/command/__init__.py
langbot_plugin/api/entities/builtin/command/context.py
langbot_plugin/api/entities/builtin/command/errors.py
langbot_plugin/api/entities/builtin/pipeline/__init__.py
langbot_plugin/api/entities/builtin/pipeline/query.py
langbot_plugin/api/entities/builtin/platform/__init__.py
langbot_plugin/api/entities/builtin/platform/entities.py
langbot_plugin/api/entities/builtin/platform/events.py
langbot_plugin/api/entities/builtin/platform/logger.py
langbot_plugin/api/entities/builtin/platform/message.py
langbot_plugin/api/entities/builtin/provider/__init__.py
langbot_plugin/api/entities/builtin/provider/message.py
langbot_plugin/api/entities/builtin/provider/prompt.py
langbot_plugin-0.2.5.dist-info/METADATA
langbot_plugin-0.2.5.dist-info/WHEEL
langbot_plugin-0.2.5.dist-info/entry_points.txt
langbot_plugin-0.2.5.dist-info/licenses/LICENSE
langbot_plugin-0.2.5.dist-info/RECORD
